[
    {
        "AssignmentStatus": "Submitted",
        "SubmitTime": "2019-04-15 19:48:36-04:00",
        "AcceptTime": "2019-04-15 19:46:30-04:00",
        "AssignmentId": "3YMU66OBIPHOIDK61AC3TLILRHKGH3",
        "Answer": "<?xml version=\"1.0\" encoding=\"ASCII\"?><QuestionFormAnswers xmlns=\"http://mechanicalturk.amazonaws.com/AWSMechanicalTurkDataSchemas/2005-10-01/QuestionFormAnswers.xsd\"><Answer><QuestionIdentifier>q1</QuestionIdentifier><FreeText>2</FreeText></Answer><Answer><QuestionIdentifier>memo</QuestionIdentifier><FreeText>skillful|skilled|skillful|44</FreeText></Answer></QuestionFormAnswers>",
        "HITId": "3VDVA3ILIEOARI1Y9I4GDE7Y4HI1GM",
        "WorkerId": "A3UVFPUB13S3JE",
        "AutoApprovalTime": "2019-05-15 19:48:36-04:00"
    }
]