[
    {
        "AssignmentStatus": "Submitted",
        "SubmitTime": "2019-04-15 16:51:34-04:00",
        "AcceptTime": "2019-04-15 16:51:13-04:00",
        "AssignmentId": "3XUHV3NRVM7Q2GVMKETCPORW185H5L",
        "Answer": "<?xml version=\"1.0\" encoding=\"ASCII\"?><QuestionFormAnswers xmlns=\"http://mechanicalturk.amazonaws.com/AWSMechanicalTurkDataSchemas/2005-10-01/QuestionFormAnswers.xsd\"><Answer><QuestionIdentifier>q1</QuestionIdentifier><FreeText>4</FreeText></Answer><Answer><QuestionIdentifier>memo</QuestionIdentifier><FreeText>manage|arrange|arrange|73</FreeText></Answer></QuestionFormAnswers>",
        "HITId": "3FDWKV9VCOBQSPOIM9CV1LWSB0RUMM",
        "WorkerId": "A3UVFPUB13S3JE",
        "AutoApprovalTime": "2019-05-15 16:51:34-04:00"
    }
]